{
    "retCode": 0,
    "retMsg": "OK",
    "result": {
        "symbol": "ETHUSD",
        "category": "inverse",
        "list": [
            [
                "1672492500000",
                "1197.2",
                "1197.45",
                "1197",
                "1197.05",
                "32988",
                "27.55358806"
            ],
            [
                "1672492200000",
                "1196.9",
                "1197.2",
                "1196.85",
                "1197.2",
                "14268",
                "11.91952191"
            ],
            [
                "1672491900000",
                "1197.1",
                "1197.1",
                "1196.85",
                "1196.9",
                "26445",
                "22.0917508"
            ],
            [
                "1672491600000",
                "1196.9",
                "1197.1",
                "1196.9",
                "1197.1",
                "38530",
                "32.18837362"
            ]
        ]
    },
    "retExtInfo": {},
    "time": 1690057604572
}